Verificacion_Javier/dff_arst.v
module dff_arst (
		input D, rst, clk,
		output reg Q
		);
always@(posedge clk, negedge rst) begin
	if(!rst) Q <= 1'b0;
	else Q <= D;
end
endmodule

Verificacion_Javier/ser_reg.v
module ser_reg #(parameter Depth = 4) (
	input rst, D_in, clk,
	output [Depth-1:0] D_out)
;
wire [Depth-1:0] d;
wire [Depth-1:0] q;
genvar i;
generate
	for (i=0;i<Depth;i=i+1) 
		begin
			dff_arst u0 (.D(d[i]), .rst(rst), .clk(clk),.Q(q[i]));
		end
endgenerate
assign d[0] = D_in;
assign d[Depth-1:1] = q[Depth-2:0];
assign D_out = q;

endmodule

Verificacion_Javier/ser_reg_tb.v
`timescale 1ns/10ps
module ser_reg_tb;
parameter Depth = 4;
reg D_in, rst_in,clk_in;
wire [Depth-1:0] D_out;
ser_reg #(.Depth(Depth)) DUT1 (
	.rst(rst_in), .D_in(D_in), .clk(clk_in),
	.D_out(D_out));
initial begin
$dumpfile("test_ser_reg.vcd");
$dumpvars(0,ser_reg_tb);
end

initial begin
forever begin
	#10
	clk_in = ~clk_in;
end
end

initial begin
D_in = 0;
clk_in = 1;
rst_in = 0;
#100
rst_in = 1;
#55
D_in = 1;
#12
rst_in = 0;
#23
rst_in = 1;
#50
D_in = 0;


$finish;
end
endmodule

Verificacion_Javier/test_ser_reg.vcd
$date
	Wed Aug 16 23:52:42 2023
$end
$version
	Icarus Verilog
$end
$timescale
	10ps
$end
$scope module ser_reg_tb $end
$var wire 4 ! D_out [3:0] $end
$var reg 1 " D_in $end
$var reg 1 # clk_in $end
$var reg 1 $ rst_in $end
$scope module DUT1 $end
$var wire 1 " D_in $end
$var wire 4 % D_out [3:0] $end
$var wire 1 # clk $end
$var wire 1 $ rst $end
$var wire 4 & q [3:0] $end
$var wire 4 ' d [3:0] $end
$scope begin genblk1[0] $end
$scope module u0 $end
$var wire 1 ( D $end
$var wire 1 # clk $end
$var wire 1 $ rst $end
$var reg 1 ) Q $end
$upscope $end
$upscope $end
$scope begin genblk1[1] $end
$scope module u0 $end
$var wire 1 * D $end
$var wire 1 # clk $end
$var wire 1 $ rst $end
$var reg 1 + Q $end
$upscope $end
$upscope $end
$scope begin genblk1[2] $end
$scope module u0 $end
$var wire 1 , D $end
$var wire 1 # clk $end
$var wire 1 $ rst $end
$var reg 1 - Q $end
$upscope $end
$upscope $end
$scope begin genblk1[3] $end
$scope module u0 $end
$var wire 1 . D $end
$var wire 1 # clk $end
$var wire 1 $ rst $end
$var reg 1 / Q $end
$upscope $end
$upscope $end
$upscope $end
$upscope $end
$enddefinitions $end
#0
$dumpvars
0/
0.
0-
0,
0+
0*
0)
0(
b0 '
b0 &
b0 %
0$
1#
0"
b0 !
$end
#1000
0#
#2000
1#
#3000
0#
#4000
1#
#5000
0#
#6000
1#
#7000
0#
#8000
1#
#9000
0#
#10000
1#
1$
#11000
0#
#12000
1#
#13000
0#
#14000
1#
#15000
0#
#15500
1(
b1 '
1"
#16000
1*
b11 '
b1 !
b1 %
b1 &
1)
1#
#16700
0*
b1 '
b0 !
b0 %
b0 &
0)
0$
#17000
0#
#18000
1#
#19000
0#
1$
#20000
1*
b11 '
b1 !
b1 %
b1 &
1)
1#
#21000
0#
#22000
1,
b111 '
b11 !
b11 %
b11 &
1+
1#
#23000
0#
#24000
1.
0*
1-
b110 !
b110 %
b110 &
0)
0(
1#
b1100 '
0"
